bigan_data/__init__.py
bigan_data/data.py
bigan_data/db/DbAdapter.py
bigan_data/db/PostgresqlAdapter.py
bigan_data/db/__init__.py
bigan_data/enum/SyncType.py
bigan_data/enum/__init__.py
bigan_data/math/GreyRelationAnalyzer.py
bigan_data/math/__init__.py
bigan_data/model/AKShareSyncModel.py
bigan_data/model/AKShareSyncModelClean.py
bigan_data/model/Df.py
bigan_data/model/GreyResult.py
bigan_data/model/Instrument.py
bigan_data/model/SyncModel.py
bigan_data/model/SyncModelClean.py
bigan_data/model/__init__.py
bigan_data/model/akshare/AKShareStockInfoACodeName.py
bigan_data/model/akshare/AKShareStockZhAHist.py
bigan_data/model/akshare/AKShareStockZhAHistHfq.py
bigan_data/model/akshare/AKShareStockZhAHistQfq.py
bigan_data/model/akshare/__init__.py
bigan_data/test/__init__.py
bigan_data/test/dbscan.py
bigan_data/test/kmeans.py
bigan_data/test/test.py
bigan_data/test/test2.py
bigan_data/test/test3.py
bigan_data-0.0.19.dist-info/METADATA
bigan_data-0.0.19.dist-info/WHEEL
bigan_data-0.0.19.dist-info/top_level.txt
bigan_data-0.0.19.dist-info/RECORD
